edag/cli/__init__.py
edag/cli/__main__.py
edag/cli/_version.py
edag/cli/cli.py
edag_cli-0.0.15.dist-info/LICENSE
edag_cli-0.0.15.dist-info/METADATA
edag_cli-0.0.15.dist-info/WHEEL
edag_cli-0.0.15.dist-info/entry_points.txt
edag_cli-0.0.15.dist-info/top_level.txt
edag_cli-0.0.15.dist-info/RECORD
