Metadata-Version: 2.1
Name: edag-cli
Version: 0.0.15
Summary: ElasticDAG CLI is the entry point for all of ElasticDAG tools.
Home-page: https://github.com/sodre/cli
Author: Patrick Sodré
Author-email: sodre@elasticdag.com
License: BSD
Keywords: cli edag
Platform: UNKNOWN
Classifier: Development Status :: 2 - Pre-Alpha
Classifier: Intended Audience :: Developers
Classifier: License :: OSI Approved :: BSD License
Classifier: Natural Language :: English
Classifier: Programming Language :: Python :: 3
Classifier: Programming Language :: Python :: 3.6
Classifier: Programming Language :: Python :: 3.7
Classifier: Programming Language :: Python :: 3.8
Requires-Python: >=3.6
Requires-Dist: click (>=7.0)
Requires-Dist: click-plugins
Requires-Dist: entrypoints
